fint_test_app/__init__.py
fint_test_app/app.py
fint_test_app/auth.py
fint_test_app/logger.py
fint_test_app/routes.py
fint_test_app-0.0.1.dist-info/METADATA
fint_test_app-0.0.1.dist-info/WHEEL
fint_test_app-0.0.1.dist-info/entry_points.txt
fint_test_app-0.0.1.dist-info/RECORD
