Metadata-Version: 2.1
Name: fint_test_app
Version: 0.0.1
Project-URL: Source, https://github.com/actfint/fint-rtc-server
Author-email: Wh1isper <9573586@qq.com>
License: BSD 3-Clause License
Keywords: fint-project
Requires-Python: >=3.7
Requires-Dist: fps>=0.0.8
Provides-Extra: test
